gbinaryclf/__init__.py
gbinaryclf/ai.py
gbinaryclf/data/Test Data.xlsx
gbinaryclf/data/Train Data.xlsx
gbinaryclf/py.typed
gbinaryclf-0.2.2.dist-info/LICENSE
gbinaryclf-0.2.2.dist-info/WHEEL
gbinaryclf-0.2.2.dist-info/METADATA
gbinaryclf-0.2.2.dist-info/RECORD
