Metadata-Version: 2.1
Name: gbinaryclf
Version: 0.2.2
Summary: Generic Python Package for Binary Classifications.
Home-page: https://github.com/altcp/gbinaryclf
License: GNU GPL v3.0
Author: altcp
Author-email: colab.tcp@gmail.com
Requires-Python: >=3.8,<4.0
Classifier: Development Status :: 3 - Alpha
Classifier: Intended Audience :: Developers
Classifier: License :: OSI Approved :: GNU General Public License v3 or later (GPLv3+)
Classifier: License :: Other/Proprietary License
Classifier: Operating System :: OS Independent
Classifier: Programming Language :: Python :: 3
Classifier: Programming Language :: Python :: 3.8
Classifier: Programming Language :: Python :: 3.9
Classifier: Topic :: Software Development :: Libraries :: Python Modules
Requires-Dist: openpyxl (>=3.0.7,<4.0.0)
Requires-Dist: pandas (>=1.3.2,<2.0.0)
Requires-Dist: scikit-learn (>=0.24.2,<0.25.0)
Requires-Dist: statsmodels (>=0.12.2,<0.13.0)
Requires-Dist: xgboost (>=1.4.2,<2.0.0)
Project-URL: Repository, https://github.com/altcp/gbinaryclf
